synology_srm/__init__.py
synology_srm/__version__.py
synology_srm/client.py
synology_srm/http.py
synology_srm/api/__init__.py
synology_srm/api/base.py
synology_srm/api/core.py
synology_srm/api/mesh.py
synology_srm-0.2.3.dist-info/LICENSE
synology_srm-0.2.3.dist-info/METADATA
synology_srm-0.2.3.dist-info/WHEEL
synology_srm-0.2.3.dist-info/top_level.txt
synology_srm-0.2.3.dist-info/RECORD
