Metadata-Version: 2.1
Name: synology-srm
Version: 0.2.3
Summary: Synology SRM API
Home-page: https://github.com/aerialls/synology-srm
Author: Julien Brochet
Author-email: julien@aerialls.eu
License: MIT
Classifier: License :: OSI Approved :: MIT License
Classifier: Programming Language :: Python
Classifier: Programming Language :: Python :: 3
Classifier: Programming Language :: Python :: 3.8
Classifier: Programming Language :: Python :: 3.9
Classifier: Programming Language :: Python :: 3.10
Classifier: Programming Language :: Python :: 3.11
Classifier: Programming Language :: Python :: Implementation :: CPython
Classifier: Programming Language :: Python :: Implementation :: PyPy
Requires-Python: >=3.8.1
License-File: LICENSE
Requires-Dist: requests
